dlg/__init__.py
dlg/dropmake/__init__.py
dlg/dropmake/definition_classes.py
dlg/dropmake/dm_utils.py
dlg/dropmake/graph_config.py
dlg/dropmake/lg.graph.schema
dlg/dropmake/lg.py
dlg/dropmake/lg_node.py
dlg/dropmake/pg_generator.py
dlg/dropmake/pg_manager.py
dlg/dropmake/pgt.py
dlg/dropmake/pgtp.py
dlg/dropmake/scheduler.py
dlg/dropmake/lib/libmetis.dylib
dlg/dropmake/lib/libmetis.so
dlg/dropmake/utils/__init__.py
dlg/dropmake/utils/anneal.py
dlg/dropmake/utils/antichains.py
dlg/dropmake/utils/bash_parameter.py
dlg/dropmake/utils/heft/base.py
dlg/dropmake/web/LICENSE
dlg/dropmake/web/__init__.py
dlg/dropmake/web/d3.v3.min.js
dlg/dropmake/web/graph_init.js
dlg/dropmake/web/license.html
dlg/dropmake/web/main.js
dlg/dropmake/web/matrix_vis.html
dlg/dropmake/web/pg_viewer.html
dlg/dropmake/web/pure-min.css
dlg/dropmake/web/translator_rest.py
dlg/dropmake/web/translator_utils.py
dlg/dropmake/web/img/jsoneditor-icons.png
dlg/dropmake/web/src/FileSaver.js
dlg/dropmake/web/src/data_prep.js
dlg/dropmake/web/src/echarts-dagre.min.js
dlg/dropmake/web/src/html2canvas.min.js
dlg/dropmake/web/src/jquery-ui.min.css
dlg/dropmake/web/src/jquery.min.js
dlg/dropmake/web/src/main.css
dlg/dropmake/web/src/require.js
dlg/dropmake/web/src/bootstrap/css/bootstrap-grid.css
dlg/dropmake/web/src/bootstrap/css/bootstrap-grid.css.map
dlg/dropmake/web/src/bootstrap/css/bootstrap-grid.min.css
dlg/dropmake/web/src/bootstrap/css/bootstrap-grid.min.css.map
dlg/dropmake/web/src/bootstrap/css/bootstrap-reboot.css
dlg/dropmake/web/src/bootstrap/css/bootstrap-reboot.css.map
dlg/dropmake/web/src/bootstrap/css/bootstrap-reboot.min.css
dlg/dropmake/web/src/bootstrap/css/bootstrap-reboot.min.css.map
dlg/dropmake/web/src/bootstrap/css/bootstrap.css
dlg/dropmake/web/src/bootstrap/css/bootstrap.css.map
dlg/dropmake/web/src/bootstrap/css/bootstrap.min.css
dlg/dropmake/web/src/bootstrap/css/bootstrap.min.css.map
dlg/dropmake/web/src/bootstrap/js/bootstrap.bundle.js
daliuge_translator-6.4.0.dist-info/METADATA
daliuge_translator-6.4.0.dist-info/WHEEL
daliuge_translator-6.4.0.dist-info/entry_points.txt
daliuge_translator-6.4.0.dist-info/top_level.txt
daliuge_translator-6.4.0.dist-info/RECORD
